ewiz/__init__.py
ewiz/algorithms/__init__.py
ewiz/algorithms/imagers/__init__.py
ewiz/algorithms/imagers/base.py
ewiz/algorithms/imagers/bilinear.py
ewiz/algorithms/imagers/count.py
ewiz/algorithms/mc/__init__.py
ewiz/algorithms/mc/base.py
ewiz/algorithms/mc/pyramidal.py
ewiz/algorithms/mc/utils.py
ewiz/algorithms/warpers/__init__.py
ewiz/algorithms/warpers/base.py
ewiz/algorithms/warpers/dense.py
ewiz/core/__init__.py
ewiz/core/props.py
ewiz/core/utils.py
ewiz/data/__init__.py
ewiz/data/converters/__init__.py
ewiz/data/converters/bag.py
ewiz/data/converters/base.py
ewiz/data/converters/dsec.py
ewiz/data/converters/mvsec.py
ewiz/data/converters/prophesee.py
ewiz/data/converters/stonefish.py
ewiz/data/encoders/__init__.py
ewiz/data/encoders/base.py
ewiz/data/encoders/gaussian.py
ewiz/data/encoders/sum.py
ewiz/data/iterators/__init__.py
ewiz/data/iterators/base.py
ewiz/data/iterators/events.py
ewiz/data/iterators/gray.py
ewiz/data/iterators/time.py
ewiz/data/readers/__init__.py
ewiz/data/readers/base.py
ewiz/data/readers/flow.py
ewiz/data/readers/utils/_sync.py
ewiz/data/readers/utils/sync.py
ewiz/data/transforms/__init__.py
ewiz/data/transforms/compose.py
ewiz/data/transforms/events.py
ewiz/data/transforms/flow.py
ewiz/data/transforms/gray.py
ewiz/data/transforms/structure.py
ewiz/data/writers/__init__.py
ewiz/data/writers/base.py
ewiz/data/writers/events.py
ewiz/data/writers/flow.py
ewiz/data/writers/gray.py
ewiz/data/writers/rgb.py
ewiz/losses/__init__.py
ewiz/losses/base.py
ewiz/losses/hybrid.py
ewiz/losses/mc.py
ewiz/losses/mse.py
ewiz/losses/photometric.py
ewiz/losses/smooth.py
ewiz/losses/sobel.py
ewiz/losses/gradient/__init__.py
ewiz/losses/gradient/gradient.py
ewiz/losses/gradient/multifocal.py
ewiz/losses/gradient/normalized.py
ewiz/losses/variance/__init__.py
ewiz/losses/variance/multifocal.py
ewiz/losses/variance/normalized.py
ewiz/losses/variance/variance.py
ewiz/metrics/__init__.py
ewiz/metrics/base.py
ewiz/metrics/endpoint.py
ewiz/renderers/__init__.py
ewiz-1.1.0.dist-info/LICENSE
ewiz-1.1.0.dist-info/METADATA
ewiz-1.1.0.dist-info/WHEEL
ewiz-1.1.0.dist-info/top_level.txt
ewiz-1.1.0.dist-info/RECORD
