Metadata-Version: 2.1
Name: ewiz
Version: 1.1.0
Summary: An all-in-one event-based data manipulation and processing library.
Author-email: Jad Mansour <jad.mansour@udg.edu>
Maintainer-email: Jad Mansour <jad.mansour@udg.edu>
License: GNU GENERAL PUBLIC LICENSE
Project-URL: Homepage, https://google.com
Project-URL: Documentation, https://readthedocs.org
Project-URL: Repository, https://github.com
Project-URL: Issues, https://github.com
Project-URL: Changelog, https://github.com
Keywords: events
Requires-Python: >=3.8
License-File: LICENSE
Requires-Dist: numpy
Requires-Dist: h5py
Requires-Dist: hdf5plugin
Requires-Dist: natsort
Requires-Dist: tqdm
Requires-Dist: matplotlib
Requires-Dist: opencv-python
Requires-Dist: pillow
Requires-Dist: scipy
Requires-Dist: scikit-image
Requires-Dist: tonic
Requires-Dist: autograd-minimize
Requires-Dist: inverse-optical-flow
Requires-Dist: flow-vis
Requires-Dist: roslibpy
Requires-Dist: bagpy
Requires-Dist: imageio-ffmpeg
